[
  {
    "ContainingType": "MachineryShop.Controllers.CategoriesController",
    "Method": "GetCategories",
    "RelativePath": "api/Categories",
    "HttpMethod": "GET",
    "IsController": true,
    "Order": 0,
    "Parameters": [],
    "ReturnTypes": [
      {
        "Type": "System.Collections.Generic.IEnumerable\u00601[[MachineryShop.Model.Category, MachineryShop, Version=1.0.0.0, Culture=neutral, PublicKeyToken=null]]",
        "MediaTypes": [
          "text/plain",
          "application/json",
          "text/json"
        ],
        "StatusCode": 200
      }
    ]
  },
  {
    "ContainingType": "MachineryShop.Controllers.CategoriesController",
    "Method": "PostCategory",
    "RelativePath": "api/Categories",
    "HttpMethod": "POST",
    "IsController": true,
    "Order": 0,
    "Parameters": [
      {
        "Name": "category",
        "Type": "MachineryShop.Model.Category",
        "IsRequired": true
      }
    ],
    "ReturnTypes": [
      {
        "Type": "MachineryShop.Model.Category",
        "MediaTypes": [
          "text/plain",
          "application/json",
          "text/json"
        ],
        "StatusCode": 200
      }
    ]
  },
  {
    "ContainingType": "MachineryShop.Controllers.CategoriesController",
    "Method": "GetCategory",
    "RelativePath": "api/Categories/{id}",
    "HttpMethod": "GET",
    "IsController": true,
    "Order": 0,
    "Parameters": [
      {
        "Name": "id",
        "Type": "System.Int32",
        "IsRequired": true
      }
    ],
    "ReturnTypes": [
      {
        "Type": "MachineryShop.Model.Category",
        "MediaTypes": [
          "text/plain",
          "application/json",
          "text/json"
        ],
        "StatusCode": 200
      }
    ]
  },
  {
    "ContainingType": "MachineryShop.Controllers.CategoriesController",
    "Method": "PutCategory",
    "RelativePath": "api/Categories/{id}",
    "HttpMethod": "PUT",
    "IsController": true,
    "Order": 0,
    "Parameters": [
      {
        "Name": "id",
        "Type": "System.Int32",
        "IsRequired": true
      },
      {
        "Name": "category",
        "Type": "MachineryShop.Model.Category",
        "IsRequired": true
      }
    ],
    "ReturnTypes": []
  },
  {
    "ContainingType": "MachineryShop.Controllers.CategoriesController",
    "Method": "DeleteCategory",
    "RelativePath": "api/Categories/{id}",
    "HttpMethod": "DELETE",
    "IsController": true,
    "Order": 0,
    "Parameters": [
      {
        "Name": "id",
        "Type": "System.Int32",
        "IsRequired": true
      }
    ],
    "ReturnTypes": []
  },
  {
    "ContainingType": "MachineryShop.Controllers.DevicesController",
    "Method": "GetDevices",
    "RelativePath": "api/Devices",
    "HttpMethod": "GET",
    "IsController": true,
    "Order": 0,
    "Parameters": [],
    "ReturnTypes": [
      {
        "Type": "System.Collections.Generic.IEnumerable\u00601[[MachineryShop.Model.Device, MachineryShop, Version=1.0.0.0, Culture=neutral, PublicKeyToken=null]]",
        "MediaTypes": [
          "text/plain",
          "application/json",
          "text/json"
        ],
        "StatusCode": 200
      }
    ]
  },
  {
    "ContainingType": "MachineryShop.Controllers.DevicesController",
    "Method": "PostDevice",
    "RelativePath": "api/Devices",
    "HttpMethod": "POST",
    "IsController": true,
    "Order": 0,
    "Parameters": [
      {
        "Name": "device",
        "Type": "MachineryShop.Model.Device",
        "IsRequired": true
      }
    ],
    "ReturnTypes": [
      {
        "Type": "MachineryShop.Model.Device",
        "MediaTypes": [
          "text/plain",
          "application/json",
          "text/json"
        ],
        "StatusCode": 200
      }
    ]
  },
  {
    "ContainingType": "MachineryShop.Controllers.DevicesController",
    "Method": "GetDevice",
    "RelativePath": "api/Devices/{id}",
    "HttpMethod": "GET",
    "IsController": true,
    "Order": 0,
    "Parameters": [
      {
        "Name": "id",
        "Type": "System.Int32",
        "IsRequired": true
      }
    ],
    "ReturnTypes": [
      {
        "Type": "MachineryShop.Model.Device",
        "MediaTypes": [
          "text/plain",
          "application/json",
          "text/json"
        ],
        "StatusCode": 200
      }
    ]
  },
  {
    "ContainingType": "MachineryShop.Controllers.DevicesController",
    "Method": "PutDevice",
    "RelativePath": "api/Devices/{id}",
    "HttpMethod": "PUT",
    "IsController": true,
    "Order": 0,
    "Parameters": [
      {
        "Name": "id",
        "Type": "System.Int32",
        "IsRequired": true
      },
      {
        "Name": "device",
        "Type": "MachineryShop.Model.Device",
        "IsRequired": true
      }
    ],
    "ReturnTypes": []
  },
  {
    "ContainingType": "MachineryShop.Controllers.DevicesController",
    "Method": "DeleteDevice",
    "RelativePath": "api/Devices/{id}",
    "HttpMethod": "DELETE",
    "IsController": true,
    "Order": 0,
    "Parameters": [
      {
        "Name": "id",
        "Type": "System.Int32",
        "IsRequired": true
      }
    ],
    "ReturnTypes": []
  },
  {
    "ContainingType": "MachineryShop.Controllers.OrdersController",
    "Method": "GetOrders",
    "RelativePath": "api/Orders",
    "HttpMethod": "GET",
    "IsController": true,
    "Order": 0,
    "Parameters": [],
    "ReturnTypes": [
      {
        "Type": "System.Collections.Generic.IEnumerable\u00601[[MachineryShop.Model.Order, MachineryShop, Version=1.0.0.0, Culture=neutral, PublicKeyToken=null]]",
        "MediaTypes": [
          "text/plain",
          "application/json",
          "text/json"
        ],
        "StatusCode": 200
      }
    ]
  },
  {
    "ContainingType": "MachineryShop.Controllers.OrdersController",
    "Method": "PostOrder",
    "RelativePath": "api/Orders",
    "HttpMethod": "POST",
    "IsController": true,
    "Order": 0,
    "Parameters": [
      {
        "Name": "order",
        "Type": "MachineryShop.Model.Order",
        "IsRequired": true
      }
    ],
    "ReturnTypes": [
      {
        "Type": "MachineryShop.Model.Order",
        "MediaTypes": [
          "text/plain",
          "application/json",
          "text/json"
        ],
        "StatusCode": 200
      }
    ]
  },
  {
    "ContainingType": "MachineryShop.Controllers.OrdersController",
    "Method": "GetOrder",
    "RelativePath": "api/Orders/{id}",
    "HttpMethod": "GET",
    "IsController": true,
    "Order": 0,
    "Parameters": [
      {
        "Name": "id",
        "Type": "System.Int32",
        "IsRequired": true
      }
    ],
    "ReturnTypes": [
      {
        "Type": "MachineryShop.Model.Order",
        "MediaTypes": [
          "text/plain",
          "application/json",
          "text/json"
        ],
        "StatusCode": 200
      }
    ]
  },
  {
    "ContainingType": "MachineryShop.Controllers.OrdersController",
    "Method": "PutOrder",
    "RelativePath": "api/Orders/{id}",
    "HttpMethod": "PUT",
    "IsController": true,
    "Order": 0,
    "Parameters": [
      {
        "Name": "id",
        "Type": "System.Int32",
        "IsRequired": true
      },
      {
        "Name": "order",
        "Type": "MachineryShop.Model.Order",
        "IsRequired": true
      }
    ],
    "ReturnTypes": []
  },
  {
    "ContainingType": "MachineryShop.Controllers.OrdersController",
    "Method": "DeleteOrder",
    "RelativePath": "api/Orders/{id}",
    "HttpMethod": "DELETE",
    "IsController": true,
    "Order": 0,
    "Parameters": [
      {
        "Name": "id",
        "Type": "System.Int32",
        "IsRequired": true
      }
    ],
    "ReturnTypes": []
  },
  {
    "ContainingType": "MachineryShop.Controllers.UsersController",
    "Method": "GetUsers",
    "RelativePath": "api/Users",
    "HttpMethod": "GET",
    "IsController": true,
    "Order": 0,
    "Parameters": [],
    "ReturnTypes": [
      {
        "Type": "System.Collections.Generic.IEnumerable\u00601[[MachineryShop.Model.User, MachineryShop, Version=1.0.0.0, Culture=neutral, PublicKeyToken=null]]",
        "MediaTypes": [
          "text/plain",
          "application/json",
          "text/json"
        ],
        "StatusCode": 200
      }
    ]
  },
  {
    "ContainingType": "MachineryShop.Controllers.UsersController",
    "Method": "PostUser",
    "RelativePath": "api/Users",
    "HttpMethod": "POST",
    "IsController": true,
    "Order": 0,
    "Parameters": [
      {
        "Name": "user",
        "Type": "MachineryShop.Model.User",
        "IsRequired": true
      }
    ],
    "ReturnTypes": [
      {
        "Type": "MachineryShop.Model.User",
        "MediaTypes": [
          "text/plain",
          "application/json",
          "text/json"
        ],
        "StatusCode": 200
      }
    ]
  },
  {
    "ContainingType": "MachineryShop.Controllers.UsersController",
    "Method": "GetUser",
    "RelativePath": "api/Users/{id}",
    "HttpMethod": "GET",
    "IsController": true,
    "Order": 0,
    "Parameters": [
      {
        "Name": "id",
        "Type": "System.Int32",
        "IsRequired": true
      }
    ],
    "ReturnTypes": [
      {
        "Type": "MachineryShop.Model.User",
        "MediaTypes": [
          "text/plain",
          "application/json",
          "text/json"
        ],
        "StatusCode": 200
      }
    ]
  },
  {
    "ContainingType": "MachineryShop.Controllers.UsersController",
    "Method": "PutUser",
    "RelativePath": "api/Users/{id}",
    "HttpMethod": "PUT",
    "IsController": true,
    "Order": 0,
    "Parameters": [
      {
        "Name": "id",
        "Type": "System.Int32",
        "IsRequired": true
      },
      {
        "Name": "user",
        "Type": "MachineryShop.Model.User",
        "IsRequired": true
      }
    ],
    "ReturnTypes": []
  },
  {
    "ContainingType": "MachineryShop.Controllers.UsersController",
    "Method": "DeleteUser",
    "RelativePath": "api/Users/{id}",
    "HttpMethod": "DELETE",
    "IsController": true,
    "Order": 0,
    "Parameters": [
      {
        "Name": "id",
        "Type": "System.Int32",
        "IsRequired": true
      }
    ],
    "ReturnTypes": []
  },
  {
    "ContainingType": "MachineryShop.Controllers.WeatherForecastController",
    "Method": "Get",
    "RelativePath": "WeatherForecast",
    "HttpMethod": "GET",
    "IsController": true,
    "Order": 0,
    "Parameters": [],
    "ReturnTypes": [
      {
        "Type": "System.Collections.Generic.IEnumerable\u00601[[MachineryShop.WeatherForecast, MachineryShop, Version=1.0.0.0, Culture=neutral, PublicKeyToken=null]]",
        "MediaTypes": [
          "text/plain",
          "application/json",
          "text/json"
        ],
        "StatusCode": 200
      }
    ]
  }
]